imgwizard/__init__.py
imgwizard/core.py
imgwizard-2025.5.100908.dist-info/licenses/LICENSE
tests/__init__.py
tests/test_core.py
imgwizard-2025.5.100908.dist-info/METADATA
imgwizard-2025.5.100908.dist-info/WHEEL
imgwizard-2025.5.100908.dist-info/top_level.txt
imgwizard-2025.5.100908.dist-info/RECORD
